odoo/addons/pos_pms_link/README.rst
odoo/addons/pos_pms_link/__init__.py
odoo/addons/pos_pms_link/__manifest__.py
odoo/addons/pos_pms_link/i18n/es.po
odoo/addons/pos_pms_link/i18n/it.po
odoo/addons/pos_pms_link/i18n/pos_pms_link.pot
odoo/addons/pos_pms_link/models/__init__.py
odoo/addons/pos_pms_link/models/pms_reservation.py
odoo/addons/pos_pms_link/models/pms_service.py
odoo/addons/pos_pms_link/models/pms_service_line.py
odoo/addons/pos_pms_link/models/pos_config.py
odoo/addons/pos_pms_link/models/pos_order.py
odoo/addons/pos_pms_link/models/pos_payment.py
odoo/addons/pos_pms_link/models/pos_session.py
odoo/addons/pos_pms_link/models/product_pricelist.py
odoo/addons/pos_pms_link/static/description/icon.png
odoo/addons/pos_pms_link/static/src/js/ReservationSelectionButton.js
odoo/addons/pos_pms_link/static/src/js/db.js
odoo/addons/pos_pms_link/static/src/js/models.js
odoo/addons/pos_pms_link/static/src/js/Screens/PaymentScreen/PaymentScreen.js
odoo/addons/pos_pms_link/static/src/js/Screens/ReceiptScreen/OrderReceipt.js
odoo/addons/pos_pms_link/static/src/js/Screens/ReservationListScreen/ReservationDetailsEdit.js
odoo/addons/pos_pms_link/static/src/js/Screens/ReservationListScreen/ReservationLine.js
odoo/addons/pos_pms_link/static/src/js/Screens/ReservationListScreen/ReservationListScreen.js
odoo/addons/pos_pms_link/static/src/xml/ReservationSelectionButton.xml
odoo/addons/pos_pms_link/static/src/xml/Screens/PaymentScreen/PaymentScreen.xml
odoo/addons/pos_pms_link/static/src/xml/Screens/ReceiptScreen/OrderReceipt.xml
odoo/addons/pos_pms_link/static/src/xml/Screens/ReservationListScreen/ReservationDetailsEdit.xml
odoo/addons/pos_pms_link/static/src/xml/Screens/ReservationListScreen/ReservationLine.xml
odoo/addons/pos_pms_link/static/src/xml/Screens/ReservationListScreen/ReservationListScreen.xml
odoo/addons/pos_pms_link/views/assets_common.xml
odoo/addons/pos_pms_link/views/pms_service_line.xml
odoo/addons/pos_pms_link/views/pos_config.xml
odoo14_addon_pos_pms_link-14.0.1.0.1.dev13.dist-info/METADATA
odoo14_addon_pos_pms_link-14.0.1.0.1.dev13.dist-info/WHEEL
odoo14_addon_pos_pms_link-14.0.1.0.1.dev13.dist-info/top_level.txt
odoo14_addon_pos_pms_link-14.0.1.0.1.dev13.dist-info/RECORD
