Metadata-Version: 2.1
Name: odoo14-addon-pos_pms_link
Version: 14.0.1.0.1.dev13
Summary: Allows to use PMS reservations on the POS interface
Home-page: https://github.com/OCA/pms
Author: Comunitea Servicios Tecnológicos S.L., Odoo Community Association (OCA)
Author-email: support@odoo-community.org
License: AGPL-3
Classifier: Programming Language :: Python
Classifier: Framework :: Odoo
Classifier: Framework :: Odoo :: 14.0
Classifier: License :: OSI Approved :: GNU Affero General Public License v3
Requires-Python: >=3.6
Requires-Dist: odoo14-addon-pms
Requires-Dist: odoo<14.1dev,>=14.0a
